filewatch/__main__.py
filewatch_cli-1.0.1.dist-info/METADATA
filewatch_cli-1.0.1.dist-info/WHEEL
filewatch_cli-1.0.1.dist-info/license.txt
filewatch_cli-1.0.1.dist-info/top_level.txt
filewatch_cli-1.0.1.dist-info/RECORD
