Metadata-Version: 2.1
Name: filewatch-cli
Version: 1.0.1
Summary: FILEWATCH is a file watcher that allows you to watch files if something changes run arguments
Home-page: https://github.com/tinasty/filewatch
Author: Adarsh Gourab Mahalik
License: MIT
Keywords: filewatch
Platform: UNKNOWN
Classifier: Programming Language :: Python :: 3
Classifier: License :: OSI Approved :: MIT License
Classifier: Operating System :: OS Independent
License-File: license.txt
Requires-Dist: click (>=8.0.4)
Requires-Dist: colorama (>=0.4.4)
Requires-Dist: commonmark (>=0.9.1)
Requires-Dist: Pygments (>=2.11.2)
Requires-Dist: rich (>=12.0.0)
